CHANGES.md
LICENSE.md
MANIFEST.in
README.md
VERSION
setup.cfg
setup.py
bin/rc.sh.bootstrap.sh
bin/rc.sh.proxy.py
bin/rc.sh.py
examples/00_connectivity.py
src/rc.connectivity.egg-info/PKG-INFO
src/rc.connectivity.egg-info/SOURCES.txt
src/rc.connectivity.egg-info/dependency_links.txt
src/rc.connectivity.egg-info/namespace_packages.txt
src/rc.connectivity.egg-info/not-zip-safe
src/rc.connectivity.egg-info/requires.txt
src/rc.connectivity.egg-info/top_level.txt
src/rc/connectivity/SDIST
src/rc/connectivity/VERSION
src/rc/connectivity/__init__.py
src/rc/connectivity/constants.py
src/rc/connectivity/piped_shell.py
src/rc/connectivity/proxy.py
src/rc/connectivity/pty2pipe.py
src/rc/connectivity/pty_shell.py
src/rc/connectivity/tunnel.py